[{
  "_id": {
    "$oid": "62ac9817b1b111fc9ac021ed"
  },
  "last_updated": {
    "$date": {
      "$numberLong": "1655683200000"
    }
  }
},{
  "_id": {
    "$oid": "62ac9cdbb1b111fc9ac021ee"
  },
  "ticker": "0001-HK",
  "name": "CKH HOLDINGS",
  "category": "Equity",
  "board_lot": 500,
  "industry_x": "Conglomerates",
  "nominal": "51.700",
  "turnover": "321.693M",
  "mkt_cap": {
    "$numberLong": "198243000000"
  },
  "pct_yield": "5.145",
  "pe_ratio": "5.943",
  "sector": null,
  "country": null,
  "website": null,
  "industry_y": null,
  "current_price": null,
  "total_cash": null,
  "total_debt": null,
  "total_revenue": null,
  "total_cash_per_share": null,
  "financial_currency": null,
  "short_name": null,
  "long_name": null,
  "exchange_timezone_name": null,
  "quote_type": null,
  "logo_url": null
},{
  "_id": {
    "$oid": "62ac9cdbb1b111fc9ac021ef"
  },
  "ticker": "0002-HK",
  "name": "CLP HOLDINGS",
  "category": "Equity",
  "board_lot": 500,
  "industry_x": "Utilities",
  "nominal": "72.850",
  "turnover": "395.673M",
  "mkt_cap": {
    "$numberLong": "184052000000"
  },
  "pct_yield": "4.255",
  "pe_ratio": "21.682",
  "sector": null,
  "country": null,
  "website": null,
  "industry_y": null,
  "current_price": null,
  "total_cash": null,
  "total_debt": null,
  "total_revenue": null,
  "total_cash_per_share": null,
  "financial_currency": null,
  "short_name": null,
  "long_name": null,
  "exchange_timezone_name": null,
  "quote_type": null,
  "logo_url": null
},{
  "_id": {
    "$oid": "62ac9cdbb1b111fc9ac021f0"
  },
  "ticker": "0003-HK",
  "name": "HK & CHINA GAS",
  "category": "Equity",
  "board_lot": 1000,
  "industry_x": "Utilities",
  "nominal": "8.250",
  "turnover": "235.385M",
  "mkt_cap": {
    "$numberLong": "153944000000"
  },
  "pct_yield": "4.242",
  "pe_ratio": "30.669",
  "sector": null,
  "country": null,
  "website": null,
  "industry_y": null,
  "current_price": null,
  "total_cash": null,
  "total_debt": null,
  "total_revenue": null,
  "total_cash_per_share": null,
  "financial_currency": null,
  "short_name": null,
  "long_name": null,
  "exchange_timezone_name": null,
  "quote_type": null,
  "logo_url": null
},{
  "_id": {
    "$oid": "62ac9cdbb1b111fc9ac021f1"
  },
  "ticker": "0004-HK",
  "name": "WHARF HOLDINGS",
  "category": "Equity",
  "board_lot": 1000,
  "industry_x": "Properties",
  "nominal": "25.700",
  "turnover": "426.913M",
  "mkt_cap": {
    "$numberLong": "78540000000"
  },
  "pct_yield": "1.556",
  "pe_ratio": "13.046",
  "sector": null,
  "country": null,
  "website": null,
  "industry_y": null,
  "current_price": null,
  "total_cash": null,
  "total_debt": null,
  "total_revenue": null,
  "total_cash_per_share": null,
  "financial_currency": null,
  "short_name": null,
  "long_name": null,
  "exchange_timezone_name": null,
  "quote_type": null,
  "logo_url": null
},{
  "_id": {
    "$oid": "62ac9cdbb1b111fc9ac021f2"
  },
  "ticker": "0005-HK",
  "name": "HSBC HOLDINGS",
  "category": "Equity",
  "board_lot": 400,
  "industry_x": "Banks",
  "nominal": "49.650",
  "turnover": "1.044B",
  "mkt_cap": {
    "$numberLong": "1013319000000"
  },
  "pct_yield": "3.928",
  "pe_ratio": "10.202",
  "sector": null,
  "country": null,
  "website": null,
  "industry_y": null,
  "current_price": null,
  "total_cash": null,
  "total_debt": null,
  "total_revenue": null,
  "total_cash_per_share": null,
  "financial_currency": null,
  "short_name": null,
  "long_name": null,
  "exchange_timezone_name": null,
  "quote_type": null,
  "logo_url": null
},{
  "_id": {
    "$oid": "62ac9cdbb1b111fc9ac021f3"
  },
  "ticker": "0006-HK",
  "name": "POWER ASSETS",
  "category": "Equity",
  "board_lot": 500,
  "industry_x": "Utilities",
  "nominal": "48.900",
  "turnover": "265.285M",
  "mkt_cap": {
    "$numberLong": "104365000000"
  },
  "pct_yield": "5.767",
  "pe_ratio": "16.979",
  "sector": null,
  "country": null,
  "website": null,
  "industry_y": null,
  "current_price": null,
  "total_cash": null,
  "total_debt": null,
  "total_revenue": null,
  "total_cash_per_share": null,
  "financial_currency": null,
  "short_name": null,
  "long_name": null,
  "exchange_timezone_name": null,
  "quote_type": null,
  "logo_url": null
},{
  "_id": {
    "$oid": "62ac9cdbb1b111fc9ac021f4"
  },
  "ticker": "0007-HK",
  "name": "WISDOM WEALTH",
  "category": "Equity",
  "board_lot": 2000,
  "industry_x": "Diversified Metals & Minerals",
  "nominal": "0.133",
  "turnover": "149,670",
  "mkt_cap": 771969000,
  "pct_yield": "0.000",
  "pe_ratio": "1.985",
  "sector": null,
  "country": null,
  "website": null,
  "industry_y": null,
  "current_price": null,
  "total_cash": null,
  "total_debt": null,
  "total_revenue": null,
  "total_cash_per_share": null,
  "financial_currency": null,
  "short_name": null,
  "long_name": null,
  "exchange_timezone_name": null,
  "quote_type": null,
  "logo_url": null
},{
  "_id": {
    "$oid": "62ac9cdbb1b111fc9ac021f5"
  },
  "ticker": "0008-HK",
  "name": "PCCW",
  "category": "Equity",
  "board_lot": 1000,
  "industry_x": "Telecommunication Services",
  "nominal": "4.090",
  "turnover": "61.311M",
  "mkt_cap": {
    "$numberLong": "31655000000"
  },
  "pct_yield": "9.059",
  "pe_ratio": "30.386",
  "sector": null,
  "country": null,
  "website": null,
  "industry_y": null,
  "current_price": null,
  "total_cash": null,
  "total_debt": null,
  "total_revenue": null,
  "total_cash_per_share": null,
  "financial_currency": null,
  "short_name": null,
  "long_name": null,
  "exchange_timezone_name": null,
  "quote_type": null,
  "logo_url": null
},{
  "_id": {
    "$oid": "62ac9cdbb1b111fc9ac021f6"
  },
  "ticker": "0009-HK",
  "name": "KEYNE LTD",
  "category": "Equity",
  "board_lot": 6000,
  "industry_x": "Properties",
  "nominal": "0.033",
  "turnover": "1,626",
  "mkt_cap": 117770000,
  "pct_yield": "0.000",
  "pe_ratio": "N/A",
  "sector": null,
  "country": null,
  "website": null,
  "industry_y": null,
  "current_price": null,
  "total_cash": null,
  "total_debt": null,
  "total_revenue": null,
  "total_cash_per_share": null,
  "financial_currency": null,
  "short_name": null,
  "long_name": null,
  "exchange_timezone_name": null,
  "quote_type": null,
  "logo_url": null
},{
  "_id": {
    "$oid": "62ac9cdbb1b111fc9ac021f7"
  },
  "ticker": "0010-HK",
  "name": "HANG LUNG GROUP",
  "category": "Equity",
  "board_lot": 1000,
  "industry_x": "Properties",
  "nominal": "14.300",
  "turnover": "13.699M",
  "mkt_cap": {
    "$numberLong": "19471000000"
  },
  "pct_yield": "6.014",
  "pe_ratio": "7.526",
  "sector": null,
  "country": null,
  "website": null,
  "industry_y": null,
  "current_price": null,
  "total_cash": null,
  "total_debt": null,
  "total_revenue": null,
  "total_cash_per_share": null,
  "financial_currency": null,
  "short_name": null,
  "long_name": null,
  "exchange_timezone_name": null,
  "quote_type": null,
  "logo_url": null
},{
  "_id": {
    "$oid": "62ac9cdbb1b111fc9ac021f8"
  },
  "ticker": "0011-HK",
  "name": "HANG SENG BANK",
  "category": "Equity",
  "board_lot": 100,
  "industry_x": "Banks",
  "nominal": "137.600",
  "turnover": "225.732M",
  "mkt_cap": {
    "$numberLong": "263070000000"
  },
  "pct_yield": "3.416",
  "pe_ratio": "19.856",
  "sector": null,
  "country": null,
  "website": null,
  "industry_y": null,
  "current_price": null,
  "total_cash": null,
  "total_debt": null,
  "total_revenue": null,
  "total_cash_per_share": null,
  "financial_currency": null,
  "short_name": null,
  "long_name": null,
  "exchange_timezone_name": null,
  "quote_type": null,
  "logo_url": null
},{
  "_id": {
    "$oid": "62ac9cdbb1b111fc9ac021f9"
  },
  "ticker": "0012-HK",
  "name": "HENDERSON LAND",
  "category": "Equity",
  "board_lot": 1000,
  "industry_x": "Properties",
  "nominal": "28.100",
  "turnover": "1.497B",
  "mkt_cap": {
    "$numberLong": "136043000000"
  },
  "pct_yield": "6.406",
  "pe_ratio": "10.293",
  "sector": null,
  "country": null,
  "website": null,
  "industry_y": null,
  "current_price": null,
  "total_cash": null,
  "total_debt": null,
  "total_revenue": null,
  "total_cash_per_share": null,
  "financial_currency": null,
  "short_name": null,
  "long_name": null,
  "exchange_timezone_name": null,
  "quote_type": null,
  "logo_url": null
},{
  "_id": {
    "$oid": "62ac9cdbb1b111fc9ac021fa"
  },
  "ticker": "0013-HK",
  "name": "HUTCHMED",
  "category": "Equity",
  "board_lot": 500,
  "industry_x": "Health Care",
  "nominal": "18.200",
  "turnover": "86.848M",
  "mkt_cap": {
    "$numberLong": "15734000000"
  },
  "pct_yield": "0.000",
  "pe_ratio": "N/A",
  "sector": null,
  "country": null,
  "website": null,
  "industry_y": null,
  "current_price": null,
  "total_cash": null,
  "total_debt": null,
  "total_revenue": null,
  "total_cash_per_share": null,
  "financial_currency": null,
  "short_name": null,
  "long_name": null,
  "exchange_timezone_name": null,
  "quote_type": null,
  "logo_url": null
},{
  "_id": {
    "$oid": "62ac9cdbb1b111fc9ac021fb"
  },
  "ticker": "0014-HK",
  "name": "HYSAN DEV",
  "category": "Equity",
  "board_lot": 1000,
  "industry_x": "Properties",
  "nominal": "22.050",
  "turnover": "139.059M",
  "mkt_cap": {
    "$numberLong": "22717000000"
  },
  "pct_yield": "6.531",
  "pe_ratio": "16.579",
  "sector": null,
  "country": null,
  "website": null,
  "industry_y": null,
  "current_price": null,
  "total_cash": null,
  "total_debt": null,
  "total_revenue": null,
  "total_cash_per_share": null,
  "financial_currency": null,
  "short_name": null,
  "long_name": null,
  "exchange_timezone_name": null,
  "quote_type": null,
  "logo_url": null
},{
  "_id": {
    "$oid": "62ac9cdbb1b111fc9ac021fc"
  },
  "ticker": "0016-HK",
  "name": "SHK PPT",
  "category": "Equity",
  "board_lot": 500,
  "industry_x": "Properties",
  "nominal": "90.700",
  "turnover": "466.268M",
  "mkt_cap": {
    "$numberLong": "262829000000"
  },
  "pct_yield": "5.458",
  "pe_ratio": "9.848",
  "sector": null,
  "country": null,
  "website": null,
  "industry_y": null,
  "current_price": null,
  "total_cash": null,
  "total_debt": null,
  "total_revenue": null,
  "total_cash_per_share": null,
  "financial_currency": null,
  "short_name": null,
  "long_name": null,
  "exchange_timezone_name": null,
  "quote_type": null,
  "logo_url": null
},{
  "_id": {
    "$oid": "62ac9cdbb1b111fc9ac021fd"
  },
  "ticker": "0017-HK",
  "name": "NEW WORLD DEV",
  "category": "Equity",
  "board_lot": 1000,
  "industry_x": "Properties",
  "nominal": "27.800",
  "turnover": "242.748M",
  "mkt_cap": {
    "$numberLong": "69962000000"
  },
  "pct_yield": "7.410",
  "pe_ratio": "60.435",
  "sector": null,
  "country": null,
  "website": null,
  "industry_y": null,
  "current_price": null,
  "total_cash": null,
  "total_debt": null,
  "total_revenue": null,
  "total_cash_per_share": null,
  "financial_currency": null,
  "short_name": null,
  "long_name": null,
  "exchange_timezone_name": null,
  "quote_type": null,
  "logo_url": null
},{
  "_id": {
    "$oid": "62ac9cdbb1b111fc9ac021fe"
  },
  "ticker": "0018-HK",
  "name": "ORIENTAL E H",
  "category": "Equity",
  "board_lot": 2000,
  "industry_x": "Media",
  "nominal": "0.700",
  "turnover": "34,700",
  "mkt_cap": 1679000000,
  "pct_yield": "14.286",
  "pe_ratio": "7.946",
  "sector": null,
  "country": null,
  "website": null,
  "industry_y": null,
  "current_price": null,
  "total_cash": null,
  "total_debt": null,
  "total_revenue": null,
  "total_cash_per_share": null,
  "financial_currency": null,
  "short_name": null,
  "long_name": null,
  "exchange_timezone_name": null,
  "quote_type": null,
  "logo_url": null
},{
  "_id": {
    "$oid": "62ac9cdbb1b111fc9ac021ff"
  },
  "ticker": "0019-HK",
  "name": "SWIRE PACIFIC A",
  "category": "Equity",
  "board_lot": 500,
  "industry_x": "Conglomerates",
  "nominal": "44.750",
  "turnover": "74.572M",
  "mkt_cap": {
    "$numberLong": "40508000000"
  },
  "pct_yield": "5.810",
  "pe_ratio": "19.889",
  "sector": null,
  "country": null,
  "website": null,
  "industry_y": null,
  "current_price": null,
  "total_cash": null,
  "total_debt": null,
  "total_revenue": null,
  "total_cash_per_share": null,
  "financial_currency": null,
  "short_name": null,
  "long_name": null,
  "exchange_timezone_name": null,
  "quote_type": null,
  "logo_url": null
},{
  "_id": {
    "$oid": "62ac9cdbb1b111fc9ac02200"
  },
  "ticker": "0020-HK",
  "name": "SENSETIME-W",
  "category": "Equity",
  "board_lot": 1000,
  "industry_x": "Software & Services",
  "nominal": "5.980",
  "turnover": "83.558M",
  "mkt_cap": {
    "$numberLong": "200374000000"
  },
  "pct_yield": "",
  "pe_ratio": "N/A",
  "sector": null,
  "country": null,
  "website": null,
  "industry_y": null,
  "current_price": null,
  "total_cash": null,
  "total_debt": null,
  "total_revenue": null,
  "total_cash_per_share": null,
  "financial_currency": null,
  "short_name": null,
  "long_name": null,
  "exchange_timezone_name": null,
  "quote_type": null,
  "logo_url": null
},{
  "_id": {
    "$oid": "62ac9cdbb1b111fc9ac02201"
  },
  "ticker": "0021-HK",
  "name": "GREAT CHI PPT",
  "category": "Equity",
  "board_lot": 5000,
  "industry_x": "Properties",
  "nominal": "0.134",
  "turnover": "0.000",
  "mkt_cap": 532681000,
  "pct_yield": "0.000",
  "pe_ratio": "N/A",
  "sector": null,
  "country": null,
  "website": null,
  "industry_y": null,
  "current_price": null,
  "total_cash": null,
  "total_debt": null,
  "total_revenue": null,
  "total_cash_per_share": null,
  "financial_currency": null,
  "short_name": null,
  "long_name": null,
  "exchange_timezone_name": null,
  "quote_type": null,
  "logo_url": null
},{
  "_id": {
    "$oid": "62ac9cdbb1b111fc9ac02202"
  },
  "ticker": "0022-HK",
  "name": "MEXAN",
  "category": "Equity",
  "board_lot": 40000,
  "industry_x": "Hotels & Restaurants & Leisure",
  "nominal": "0.097",
  "turnover": "3,920",
  "mkt_cap": 190740000,
  "pct_yield": "0.000",
  "pe_ratio": "N/A",
  "sector": null,
  "country": null,
  "website": null,
  "industry_y": null,
  "current_price": null,
  "total_cash": null,
  "total_debt": null,
  "total_revenue": null,
  "total_cash_per_share": null,
  "financial_currency": null,
  "short_name": null,
  "long_name": null,
  "exchange_timezone_name": null,
  "quote_type": null,
  "logo_url": null
},{
  "_id": {
    "$oid": "62ac9cdbb1b111fc9ac02203"
  },
  "ticker": "0023-HK",
  "name": "BANK OF E ASIA",
  "category": "Equity",
  "board_lot": 200,
  "industry_x": "Banks",
  "nominal": "11.140",
  "turnover": "137.634M",
  "mkt_cap": {
    "$numberLong": "29950000000"
  },
  "pct_yield": "6.284",
  "pe_ratio": "7.281",
  "sector": null,
  "country": null,
  "website": null,
  "industry_y": null,
  "current_price": null,
  "total_cash": null,
  "total_debt": null,
  "total_revenue": null,
  "total_cash_per_share": null,
  "financial_currency": null,
  "short_name": null,
  "long_name": null,
  "exchange_timezone_name": null,
  "quote_type": null,
  "logo_url": null
},{
  "_id": {
    "$oid": "62ac9cdbb1b111fc9ac02204"
  },
  "ticker": "0025-HK",
  "name": "CHEVALIER INT'L",
  "category": "Equity",
  "board_lot": 2000,
  "industry_x": "Conglomerates",
  "nominal": "9.100",
  "turnover": "5,946",
  "mkt_cap": {
    "$numberLong": "2748000000"
  },
  "pct_yield": "5.934",
  "pe_ratio": "4.293",
  "sector": null,
  "country": null,
  "website": null,
  "industry_y": null,
  "current_price": null,
  "total_cash": null,
  "total_debt": null,
  "total_revenue": null,
  "total_cash_per_share": null,
  "financial_currency": null,
  "short_name": null,
  "long_name": null,
  "exchange_timezone_name": null,
  "quote_type": null,
  "logo_url": null
},{
  "_id": {
    "$oid": "62ac9cdbb1b111fc9ac02205"
  },
  "ticker": "0026-HK",
  "name": "CHINA MOTOR BUS",
  "category": "Equity",
  "board_lot": 200,
  "industry_x": "Properties",
  "nominal": "90.000",
  "turnover": "0.000",
  "mkt_cap": {
    "$numberLong": "4078000000"
  },
  "pct_yield": "3.556",
  "pe_ratio": "N/A",
  "sector": null,
  "country": null,
  "website": null,
  "industry_y": null,
  "current_price": null,
  "total_cash": null,
  "total_debt": null,
  "total_revenue": null,
  "total_cash_per_share": null,
  "financial_currency": null,
  "short_name": null,
  "long_name": null,
  "exchange_timezone_name": null,
  "quote_type": null,
  "logo_url": null
},{
  "_id": {
    "$oid": "62ac9cdbb1b111fc9ac02206"
  },
  "ticker": "0027-HK",
  "name": "GALAXY ENT",
  "category": "Equity",
  "board_lot": 1000,
  "industry_x": "Hotels & Restaurants & Leisure",
  "nominal": "40.800",
  "turnover": "225.525M",
  "mkt_cap": {
    "$numberLong": "177919000000"
  },
  "pct_yield": "0.735",
  "pe_ratio": "133.771",
  "sector": null,
  "country": null,
  "website": null,
  "industry_y": null,
  "current_price": null,
  "total_cash": null,
  "total_debt": null,
  "total_revenue": null,
  "total_cash_per_share": null,
  "financial_currency": null,
  "short_name": null,
  "long_name": null,
  "exchange_timezone_name": null,
  "quote_type": null,
  "logo_url": null
},{
  "_id": {
    "$oid": "62ac9cdbb1b111fc9ac02207"
  },
  "ticker": "0028-HK",
  "name": "TIAN AN",
  "category": "Equity",
  "board_lot": 1000,
  "industry_x": "Properties",
  "nominal": "3.970",
  "turnover": "11,990",
  "mkt_cap": {
    "$numberLong": "5820000000"
  },
  "pct_yield": "5.038",
  "pe_ratio": "4.135",
  "sector": null,
  "country": null,
  "website": null,
  "industry_y": null,
  "current_price": null,
  "total_cash": null,
  "total_debt": null,
  "total_revenue": null,
  "total_cash_per_share": null,
  "financial_currency": null,
  "short_name": null,
  "long_name": null,
  "exchange_timezone_name": null,
  "quote_type": null,
  "logo_url": null
},{
  "_id": {
    "$oid": "62ac9cdbb1b111fc9ac02208"
  },
  "ticker": "0029-HK",
  "name": "DYNAMIC HOLD",
  "category": "Equity",
  "board_lot": 2000,
  "industry_x": "Properties",
  "nominal": "9.230",
  "turnover": "0.000",
  "mkt_cap": {
    "$numberLong": "2194000000"
  },
  "pct_yield": "0.163",
  "pe_ratio": "N/A",
  "sector": null,
  "country": null,
  "website": null,
  "industry_y": null,
  "current_price": null,
  "total_cash": null,
  "total_debt": null,
  "total_revenue": null,
  "total_cash_per_share": null,
  "financial_currency": null,
  "short_name": null,
  "long_name": null,
  "exchange_timezone_name": null,
  "quote_type": null,
  "logo_url": null
},{
  "_id": {
    "$oid": "62ac9cdbb1b111fc9ac02209"
  },
  "ticker": "0030-HK",
  "name": "BAN LOONG HOLD",
  "category": "Equity",
  "board_lot": 2000,
  "industry_x": "Food & Beverages",
  "nominal": "0.250",
  "turnover": "149,634",
  "mkt_cap": 1700000000,
  "pct_yield": "0.000",
  "pe_ratio": "125.000",
  "sector": null,
  "country": null,
  "website": null,
  "industry_y": null,
  "current_price": null,
  "total_cash": null,
  "total_debt": null,
  "total_revenue": null,
  "total_cash_per_share": null,
  "financial_currency": null,
  "short_name": null,
  "long_name": null,
  "exchange_timezone_name": null,
  "quote_type": null,
  "logo_url": null
},{
  "_id": {
    "$oid": "62ac9cdbb1b111fc9ac0220a"
  },
  "ticker": "0031-HK",
  "name": "CHINA AEROSPACE",
  "category": "Equity",
  "board_lot": 2000,
  "industry_x": "Industrials",
  "nominal": "0.490",
  "turnover": "258,090",
  "mkt_cap": 1512000000,
  "pct_yield": "4.082",
  "pe_ratio": "4.371",
  "sector": null,
  "country": null,
  "website": null,
  "industry_y": null,
  "current_price": null,
  "total_cash": null,
  "total_debt": null,
  "total_revenue": null,
  "total_cash_per_share": null,
  "financial_currency": null,
  "short_name": null,
  "long_name": null,
  "exchange_timezone_name": null,
  "quote_type": null,
  "logo_url": null
},{
  "_id": {
    "$oid": "62ac9cdbb1b111fc9ac0220b"
  },
  "ticker": "0032-HK",
  "name": "CROSS-HAR(HOLD)",
  "category": "Equity",
  "board_lot": 1000,
  "industry_x": "Commercial & Professional Services",
  "nominal": "11.000",
  "turnover": "33,000",
  "mkt_cap": {
    "$numberLong": "4099999999"
  },
  "pct_yield": "3.818",
  "pe_ratio": "N/A",
  "sector": null,
  "country": null,
  "website": null,
  "industry_y": null,
  "current_price": null,
  "total_cash": null,
  "total_debt": null,
  "total_revenue": null,
  "total_cash_per_share": null,
  "financial_currency": null,
  "short_name": null,
  "long_name": null,
  "exchange_timezone_name": null,
  "quote_type": null,
  "logo_url": null
},{
  "_id": {
    "$oid": "62ac9cdbb1b111fc9ac0220c"
  },
  "ticker": "0033-HK",
  "name": "AMBER HILL FIN",
  "category": "Equity",
  "board_lot": 6000,
  "industry_x": "Household & Personal Products",
  "nominal": "1.880",
  "turnover": "259,184",
  "mkt_cap": 1010000000,
  "pct_yield": "0.000",
  "pe_ratio": "N/A",
  "sector": null,
  "country": null,
  "website": null,
  "industry_y": null,
  "current_price": null,
  "total_cash": null,
  "total_debt": null,
  "total_revenue": null,
  "total_cash_per_share": null,
  "financial_currency": null,
  "short_name": null,
  "long_name": null,
  "exchange_timezone_name": null,
  "quote_type": null,
  "logo_url": null
},{
  "_id": {
    "$oid": "62ac9cdbb1b111fc9ac0220d"
  },
  "ticker": "0034-HK",
  "name": "KOWLOON DEV",
  "category": "Equity",
  "board_lot": 1000,
  "industry_x": "Properties",
  "nominal": "10.400",
  "turnover": "3.322M",
  "mkt_cap": {
    "$numberLong": "12237000000"
  },
  "pct_yield": "7.885",
  "pe_ratio": "5.532",
  "sector": null,
  "country": null,
  "website": null,
  "industry_y": null,
  "current_price": null,
  "total_cash": null,
  "total_debt": null,
  "total_revenue": null,
  "total_cash_per_share": null,
  "financial_currency": null,
  "short_name": null,
  "long_name": null,
  "exchange_timezone_name": null,
  "quote_type": null,
  "logo_url": null
},{
  "_id": {
    "$oid": "62ac9cdbb1b111fc9ac0220e"
  },
  "ticker": "0035-HK",
  "name": "FE CONSORT INTL",
  "category": "Equity",
  "board_lot": 1000,
  "industry_x": "Properties",
  "nominal": "2.310",
  "turnover": "3.502M",
  "mkt_cap": {
    "$numberLong": "5589000000"
  },
  "pct_yield": "8.225",
  "pe_ratio": "10.087",
  "sector": null,
  "country": null,
  "website": null,
  "industry_y": null,
  "current_price": null,
  "total_cash": null,
  "total_debt": null,
  "total_revenue": null,
  "total_cash_per_share": null,
  "financial_currency": null,
  "short_name": null,
  "long_name": null,
  "exchange_timezone_name": null,
  "quote_type": null,
  "logo_url": null
},{
  "_id": {
    "$oid": "62ac9cdbb1b111fc9ac0220f"
  },
  "ticker": "0036-HK",
  "name": "FE HLDGS INTL",
  "category": "Equity",
  "board_lot": 3000,
  "industry_x": "Properties",
  "nominal": "0.129",
  "turnover": "9,774",
  "mkt_cap": 140496000,
  "pct_yield": "0.000",
  "pe_ratio": "N/A",
  "sector": null,
  "country": null,
  "website": null,
  "industry_y": null,
  "current_price": null,
  "total_cash": null,
  "total_debt": null,
  "total_revenue": null,
  "total_cash_per_share": null,
  "financial_currency": null,
  "short_name": null,
  "long_name": null,
  "exchange_timezone_name": null,
  "quote_type": null,
  "logo_url": null
},{
  "_id": {
    "$oid": "62ac9cdbb1b111fc9ac02210"
  },
  "ticker": "0037-HK",
  "name": "FE HOTELS",
  "category": "Equity",
  "board_lot": 2000,
  "industry_x": "Properties",
  "nominal": "0.850",
  "turnover": "1.095M",
  "mkt_cap": 636250000,
  "pct_yield": "0.000",
  "pe_ratio": "65.892",
  "sector": null,
  "country": null,
  "website": null,
  "industry_y": null,
  "current_price": null,
  "total_cash": null,
  "total_debt": null,
  "total_revenue": null,
  "total_cash_per_share": null,
  "financial_currency": null,
  "short_name": null,
  "long_name": null,
  "exchange_timezone_name": null,
  "quote_type": null,
  "logo_url": null
},{
  "_id": {
    "$oid": "62ac9cdbb1b111fc9ac02211"
  },
  "ticker": "0038-HK",
  "name": "FIRST TRACTOR",
  "category": "Equity",
  "board_lot": 2000,
  "industry_x": "Industrials",
  "nominal": "3.610",
  "turnover": "3.249M",
  "mkt_cap": 1415000000,
  "pct_yield": "3.986",
  "pe_ratio": "7.833",
  "sector": null,
  "country": null,
  "website": null,
  "industry_y": null,
  "current_price": null,
  "total_cash": null,
  "total_debt": null,
  "total_revenue": null,
  "total_cash_per_share": null,
  "financial_currency": null,
  "short_name": null,
  "long_name": null,
  "exchange_timezone_name": null,
  "quote_type": null,
  "logo_url": null
},{
  "_id": {
    "$oid": "62ac9cdbb1b111fc9ac02212"
  },
  "ticker": "0039-HK",
  "name": "CH BEIDAHUANG",
  "category": "Equity",
  "board_lot": 8000,
  "industry_x": "Food & Beverages",
  "nominal": "0.069",
  "turnover": "218,082",
  "mkt_cap": 429534000,
  "pct_yield": "0.000",
  "pe_ratio": "N/A",
  "sector": null,
  "country": null,
  "website": null,
  "industry_y": null,
  "current_price": null,
  "total_cash": null,
  "total_debt": null,
  "total_revenue": null,
  "total_cash_per_share": null,
  "financial_currency": null,
  "short_name": null,
  "long_name": null,
  "exchange_timezone_name": null,
  "quote_type": null,
  "logo_url": null
},{
  "_id": {
    "$oid": "62ac9cdbb1b111fc9ac02213"
  },
  "ticker": "0040-HK",
  "name": "GOLD PEAK",
  "category": "Equity",
  "board_lot": 1000,
  "industry_x": "Household Appliances & Electronics",
  "nominal": "0.630",
  "turnover": "314,970",
  "mkt_cap": 576749000,
  "pct_yield": "0.000",
  "pe_ratio": "4.083",
  "sector": null,
  "country": null,
  "website": null,
  "industry_y": null,
  "current_price": null,
  "total_cash": null,
  "total_debt": null,
  "total_revenue": null,
  "total_cash_per_share": null,
  "financial_currency": null,
  "short_name": null,
  "long_name": null,
  "exchange_timezone_name": null,
  "quote_type": null,
  "logo_url": null
},{
  "_id": {
    "$oid": "62ac9cdbb1b111fc9ac02214"
  },
  "ticker": "0041-HK",
  "name": "GREAT EAGLE H",
  "category": "Equity",
  "board_lot": 1000,
  "industry_x": "Properties",
  "nominal": "17.040",
  "turnover": "5.676M",
  "mkt_cap": {
    "$numberLong": "12457000000"
  },
  "pct_yield": "7.805",
  "pe_ratio": "N/A",
  "sector": null,
  "country": null,
  "website": null,
  "industry_y": null,
  "current_price": null,
  "total_cash": null,
  "total_debt": null,
  "total_revenue": null,
  "total_cash_per_share": null,
  "financial_currency": null,
  "short_name": null,
  "long_name": null,
  "exchange_timezone_name": null,
  "quote_type": null,
  "logo_url": null
},{
  "_id": {
    "$oid": "62ac9cdbb1b111fc9ac02215"
  },
  "ticker": "0042-HK",
  "name": "NE ELECTRIC",
  "category": "Equity",
  "board_lot": 2000,
  "industry_x": "Industrials",
  "nominal": "0.265",
  "turnover": "9,420",
  "mkt_cap": 68357000,
  "pct_yield": "0.000",
  "pe_ratio": "11.215",
  "sector": null,
  "country": null,
  "website": null,
  "industry_y": null,
  "current_price": null,
  "total_cash": null,
  "total_debt": null,
  "total_revenue": null,
  "total_cash_per_share": null,
  "financial_currency": null,
  "short_name": null,
  "long_name": null,
  "exchange_timezone_name": null,
  "quote_type": null,
  "logo_url": null
},{
  "_id": {
    "$oid": "62ac9cdbb1b111fc9ac02216"
  },
  "ticker": "0045-HK",
  "name": "HK&S HOTELS",
  "category": "Equity",
  "board_lot": 500,
  "industry_x": "Hotels & Restaurants & Leisure",
  "nominal": "6.930",
  "turnover": "4.617M",
  "mkt_cap": {
    "$numberLong": "11431000000"
  },
  "pct_yield": "0.000",
  "pe_ratio": "N/A",
  "sector": null,
  "country": null,
  "website": null,
  "industry_y": null,
  "current_price": null,
  "total_cash": null,
  "total_debt": null,
  "total_revenue": null,
  "total_cash_per_share": null,
  "financial_currency": null,
  "short_name": null,
  "long_name": null,
  "exchange_timezone_name": null,
  "quote_type": null,
  "logo_url": null
},{
  "_id": {
    "$oid": "62ac9cdbb1b111fc9ac02217"
  },
  "ticker": "0046-HK",
  "name": "COMPUTER & TECH",
  "category": "Equity",
  "board_lot": 2000,
  "industry_x": "Software & Services",
  "nominal": "2.480",
  "turnover": "0.000",
  "mkt_cap": 618731000,
  "pct_yield": "6.855",
  "pe_ratio": "11.397",
  "sector": null,
  "country": null,
  "website": null,
  "industry_y": null,
  "current_price": null,
  "total_cash": null,
  "total_debt": null,
  "total_revenue": null,
  "total_cash_per_share": null,
  "financial_currency": null,
  "short_name": null,
  "long_name": null,
  "exchange_timezone_name": null,
  "quote_type": null,
  "logo_url": null
},{
  "_id": {
    "$oid": "62ac9cdbb1b111fc9ac02218"
  },
  "ticker": "0048-HK",
  "name": "C AUTO INT DECO",
  "category": "Equity",
  "board_lot": 10000,
  "industry_x": "Automobiles",
  "nominal": "0.530",
  "turnover": "0.000",
  "mkt_cap": 92811000,
  "pct_yield": "0.000",
  "pe_ratio": "N/A",
  "sector": null,
  "country": null,
  "website": null,
  "industry_y": null,
  "current_price": null,
  "total_cash": null,
  "total_debt": null,
  "total_revenue": null,
  "total_cash_per_share": null,
  "financial_currency": null,
  "short_name": null,
  "long_name": null,
  "exchange_timezone_name": null,
  "quote_type": null,
  "logo_url": null
},{
  "_id": {
    "$oid": "62ac9cdbb1b111fc9ac02219"
  },
  "ticker": "0050-HK",
  "name": "HK FERRY (HOLD)",
  "category": "Equity",
  "board_lot": 1000,
  "industry_x": "Properties",
  "nominal": "6.940",
  "turnover": "235,350",
  "mkt_cap": {
    "$numberLong": "2473000000"
  },
  "pct_yield": "18.012",
  "pe_ratio": "21.030",
  "sector": null,
  "country": null,
  "website": null,
  "industry_y": null,
  "current_price": null,
  "total_cash": null,
  "total_debt": null,
  "total_revenue": null,
  "total_cash_per_share": null,
  "financial_currency": null,
  "short_name": null,
  "long_name": null,
  "exchange_timezone_name": null,
  "quote_type": null,
  "logo_url": null
},{
  "_id": {
    "$oid": "62ac9cdbb1b111fc9ac0221a"
  },
  "ticker": "0051-HK",
  "name": "HARBOUR CENTRE",
  "category": "Equity",
  "board_lot": 1000,
  "industry_x": "Properties",
  "nominal": "7.000",
  "turnover": "371,000",
  "mkt_cap": {
    "$numberLong": "4961000000"
  },
  "pct_yield": "0.000",
  "pe_ratio": "N/A",
  "sector": null,
  "country": null,
  "website": null,
  "industry_y": null,
  "current_price": null,
  "total_cash": null,
  "total_debt": null,
  "total_revenue": null,
  "total_cash_per_share": null,
  "financial_currency": null,
  "short_name": null,
  "long_name": null,
  "exchange_timezone_name": null,
  "quote_type": null,
  "logo_url": null
},{
  "_id": {
    "$oid": "62ac9cdbb1b111fc9ac0221b"
  },
  "ticker": "0052-HK",
  "name": "FAIRWOOD HOLD",
  "category": "Equity",
  "board_lot": 500,
  "industry_x": "Hotels & Restaurants & Leisure",
  "nominal": "13.620",
  "turnover": "524,950",
  "mkt_cap": 1765000000,
  "pct_yield": "6.241",
  "pe_ratio": "11.485",
  "sector": null,
  "country": null,
  "website": null,
  "industry_y": null,
  "current_price": null,
  "total_cash": null,
  "total_debt": null,
  "total_revenue": null,
  "total_cash_per_share": null,
  "financial_currency": null,
  "short_name": null,
  "long_name": null,
  "exchange_timezone_name": null,
  "quote_type": null,
  "logo_url": null
},{
  "_id": {
    "$oid": "62ac9cdbb1b111fc9ac0221c"
  },
  "ticker": "0053-HK",
  "name": "GUOCO GROUP",
  "category": "Equity",
  "board_lot": 1000,
  "industry_x": "Properties",
  "nominal": "81.000",
  "turnover": "2.075M",
  "mkt_cap": {
    "$numberLong": "26653000000"
  },
  "pct_yield": "2.469",
  "pe_ratio": "10.423",
  "sector": null,
  "country": null,
  "website": null,
  "industry_y": null,
  "current_price": null,
  "total_cash": null,
  "total_debt": null,
  "total_revenue": null,
  "total_cash_per_share": null,
  "financial_currency": null,
  "short_name": null,
  "long_name": null,
  "exchange_timezone_name": null,
  "quote_type": null,
  "logo_url": null
},{
  "_id": {
    "$oid": "62ac9cdbb1b111fc9ac0221d"
  },
  "ticker": "0055-HK",
  "name": "NEWAY GROUP",
  "category": "Equity",
  "board_lot": 10000,
  "industry_x": "Industrials",
  "nominal": "0.390",
  "turnover": "7,850",
  "mkt_cap": 98919000,
  "pct_yield": "0.000",
  "pe_ratio": "N/A",
  "sector": null,
  "country": null,
  "website": null,
  "industry_y": null,
  "current_price": null,
  "total_cash": null,
  "total_debt": null,
  "total_revenue": null,
  "total_cash_per_share": null,
  "financial_currency": null,
  "short_name": null,
  "long_name": null,
  "exchange_timezone_name": null,
  "quote_type": null,
  "logo_url": null
},{
  "_id": {
    "$oid": "62ac9cdbb1b111fc9ac0221e"
  },
  "ticker": "0057-HK",
  "name": "CHEN HSONG HOLD",
  "category": "Equity",
  "board_lot": 2000,
  "industry_x": "Industrials",
  "nominal": "2.680",
  "turnover": "2.861M",
  "mkt_cap": 1690000000,
  "pct_yield": "6.231",
  "pe_ratio": "8.323",
  "sector": null,
  "country": null,
  "website": null,
  "industry_y": null,
  "current_price": null,
  "total_cash": null,
  "total_debt": null,
  "total_revenue": null,
  "total_cash_per_share": null,
  "financial_currency": null,
  "short_name": null,
  "long_name": null,
  "exchange_timezone_name": null,
  "quote_type": null,
  "logo_url": null
},{
  "_id": {
    "$oid": "62ac9cdbb1b111fc9ac0221f"
  },
  "ticker": "0058-HK",
  "name": "SUNWAY INT'L",
  "category": "Equity",
  "board_lot": 20000,
  "industry_x": "Construction",
  "nominal": "0.150",
  "turnover": "0.000",
  "mkt_cap": 26940000,
  "pct_yield": "0.000",
  "pe_ratio": "N/A",
  "sector": null,
  "country": null,
  "website": null,
  "industry_y": null,
  "current_price": null,
  "total_cash": null,
  "total_debt": null,
  "total_revenue": null,
  "total_cash_per_share": null,
  "financial_currency": null,
  "short_name": null,
  "long_name": null,
  "exchange_timezone_name": null,
  "quote_type": null,
  "logo_url": null
},{
  "_id": {
    "$oid": "62ac9cdbb1b111fc9ac02220"
  },
  "ticker": "0059-HK",
  "name": "SKYFAME REALTY",
  "category": "Equity",
  "board_lot": 2000,
  "industry_x": "Properties",
  "nominal": "0.089",
  "turnover": "217.516M",
  "mkt_cap": 751723000,
  "pct_yield": "0.000",
  "pe_ratio": "N/A",
  "sector": null,
  "country": null,
  "website": null,
  "industry_y": null,
  "current_price": null,
  "total_cash": null,
  "total_debt": null,
  "total_revenue": null,
  "total_cash_per_share": null,
  "financial_currency": null,
  "short_name": null,
  "long_name": null,
  "exchange_timezone_name": null,
  "quote_type": null,
  "logo_url": null
},{
  "_id": {
    "$oid": "62ac9cdbb1b111fc9ac02221"
  },
  "ticker": "0060-HK",
  "name": "HK FOOD INV",
  "category": "Equity",
  "board_lot": 2000,
  "industry_x": "Food & Beverages",
  "nominal": "0.540",
  "turnover": "1,100",
  "mkt_cap": 140176000,
  "pct_yield": "0.000",
  "pe_ratio": "N/A",
  "sector": null,
  "country": null,
  "website": null,
  "industry_y": null,
  "current_price": null,
  "total_cash": null,
  "total_debt": null,
  "total_revenue": null,
  "total_cash_per_share": null,
  "financial_currency": null,
  "short_name": null,
  "long_name": null,
  "exchange_timezone_name": null,
  "quote_type": null,
  "logo_url": null
},{
  "_id": {
    "$oid": "62ac9cdbb1b111fc9ac02222"
  },
  "ticker": "0061-HK",
  "name": "GREEN LEADER",
  "category": "Equity",
  "board_lot": 20000,
  "industry_x": "Coal",
  "nominal": "0.100",
  "turnover": "1,173",
  "mkt_cap": 52626000,
  "pct_yield": "0.000",
  "pe_ratio": "0.200",
  "sector": null,
  "country": null,
  "website": null,
  "industry_y": null,
  "current_price": null,
  "total_cash": null,
  "total_debt": null,
  "total_revenue": null,
  "total_cash_per_share": null,
  "financial_currency": null,
  "short_name": null,
  "long_name": null,
  "exchange_timezone_name": null,
  "quote_type": null,
  "logo_url": null
},{
  "_id": {
    "$oid": "62ac9cdbb1b111fc9ac02223"
  },
  "ticker": "0062-HK",
  "name": "TRANSPORT INT'L",
  "category": "Equity",
  "board_lot": 400,
  "industry_x": "Transportation",
  "nominal": "11.900",
  "turnover": "562,878",
  "mkt_cap": {
    "$numberLong": "5539000000"
  },
  "pct_yield": "4.202",
  "pe_ratio": "22.453",
  "sector": null,
  "country": null,
  "website": null,
  "industry_y": null,
  "current_price": null,
  "total_cash": null,
  "total_debt": null,
  "total_revenue": null,
  "total_cash_per_share": null,
  "financial_currency": null,
  "short_name": null,
  "long_name": null,
  "exchange_timezone_name": null,
  "quote_type": null,
  "logo_url": null
},{
  "_id": {
    "$oid": "62ac9cdbb1b111fc9ac02224"
  },
  "ticker": "0063-HK",
  "name": "CHI ASIA VALLEY",
  "category": "Equity",
  "board_lot": 1000,
  "industry_x": "Properties",
  "nominal": "0.078",
  "turnover": "28,919",
  "mkt_cap": 219890000,
  "pct_yield": "0.000",
  "pe_ratio": "N/A",
  "sector": null,
  "country": null,
  "website": null,
  "industry_y": null,
  "current_price": null,
  "total_cash": null,
  "total_debt": null,
  "total_revenue": null,
  "total_cash_per_share": null,
  "financial_currency": null,
  "short_name": null,
  "long_name": null,
  "exchange_timezone_name": null,
  "quote_type": null,
  "logo_url": null
},{
  "_id": {
    "$oid": "62ac9cdbb1b111fc9ac02225"
  },
  "ticker": "0064-HK",
  "name": "GET NICE",
  "category": "Equity",
  "board_lot": 2000,
  "industry_x": "Other Financials",
  "nominal": "0.156",
  "turnover": "181,032",
  "mkt_cap": 1507000000,
  "pct_yield": "6.410",
  "pe_ratio": "7.959",
  "sector": null,
  "country": null,
  "website": null,
  "industry_y": null,
  "current_price": null,
  "total_cash": null,
  "total_debt": null,
  "total_revenue": null,
  "total_cash_per_share": null,
  "financial_currency": null,
  "short_name": null,
  "long_name": null,
  "exchange_timezone_name": null,
  "quote_type": null,
  "logo_url": null
},{
  "_id": {
    "$oid": "62ac9cdbb1b111fc9ac02226"
  },
  "ticker": "0065-HK",
  "name": "GRAND OCEAN AR",
  "category": "Equity",
  "board_lot": 4000,
  "industry_x": "Coal",
  "nominal": "0.167",
  "turnover": "4,878",
  "mkt_cap": 251081000,
  "pct_yield": "0.000",
  "pe_ratio": "17.396",
  "sector": null,
  "country": null,
  "website": null,
  "industry_y": null,
  "current_price": null,
  "total_cash": null,
  "total_debt": null,
  "total_revenue": null,
  "total_cash_per_share": null,
  "financial_currency": null,
  "short_name": null,
  "long_name": null,
  "exchange_timezone_name": null,
  "quote_type": null,
  "logo_url": null
},{
  "_id": {
    "$oid": "62ac9cdbb1b111fc9ac02227"
  },
  "ticker": "0066-HK",
  "name": "MTR CORPORATION",
  "category": "Equity",
  "board_lot": 500,
  "industry_x": "Transportation",
  "nominal": "40.700",
  "turnover": "155.830M",
  "mkt_cap": {
    "$numberLong": "252074000000"
  },
  "pct_yield": "3.120",
  "pe_ratio": "26.258",
  "sector": null,
  "country": null,
  "website": null,
  "industry_y": null,
  "current_price": null,
  "total_cash": null,
  "total_debt": null,
  "total_revenue": null,
  "total_cash_per_share": null,
  "financial_currency": null,
  "short_name": null,
  "long_name": null,
  "exchange_timezone_name": null,
  "quote_type": null,
  "logo_url": null
},{
  "_id": {
    "$oid": "62ac9cdbb1b111fc9ac02228"
  },
  "ticker": "0068-HK",
  "name": "LEE HING",
  "category": "Equity",
  "board_lot": 1000,
  "industry_x": "Other Financials",
  "nominal": "0.520",
  "turnover": "0.000",
  "mkt_cap": 76326000,
  "pct_yield": "0.000",
  "pe_ratio": "N/A",
  "sector": null,
  "country": null,
  "website": null,
  "industry_y": null,
  "current_price": null,
  "total_cash": null,
  "total_debt": null,
  "total_revenue": null,
  "total_cash_per_share": null,
  "financial_currency": null,
  "short_name": null,
  "long_name": null,
  "exchange_timezone_name": null,
  "quote_type": null,
  "logo_url": null
},{
  "_id": {
    "$oid": "62ac9cdbb1b111fc9ac02229"
  },
  "ticker": "0069-HK",
  "name": "SHANGRI-LA ASIA",
  "category": "Equity",
  "board_lot": 2000,
  "industry_x": "Hotels & Restaurants & Leisure",
  "nominal": "6.160",
  "turnover": "5.833M",
  "mkt_cap": {
    "$numberLong": "22087000000"
  },
  "pct_yield": "0.000",
  "pe_ratio": "N/A",
  "sector": null,
  "country": null,
  "website": null,
  "industry_y": null,
  "current_price": null,
  "total_cash": null,
  "total_debt": null,
  "total_revenue": null,
  "total_cash_per_share": null,
  "financial_currency": null,
  "short_name": null,
  "long_name": null,
  "exchange_timezone_name": null,
  "quote_type": null,
  "logo_url": null
},{
  "_id": {
    "$oid": "62ac9cdbb1b111fc9ac0222a"
  },
  "ticker": "0070-HK",
  "name": "RICH GOLDMAN",
  "category": "Equity",
  "board_lot": 10000,
  "industry_x": "Hotels & Restaurants & Leisure",
  "nominal": "0.055",
  "turnover": "0.000",
  "mkt_cap": 106635000,
  "pct_yield": "0.000",
  "pe_ratio": "N/A",
  "sector": null,
  "country": null,
  "website": null,
  "industry_y": null,
  "current_price": null,
  "total_cash": null,
  "total_debt": null,
  "total_revenue": null,
  "total_cash_per_share": null,
  "financial_currency": null,
  "short_name": null,
  "long_name": null,
  "exchange_timezone_name": null,
  "quote_type": null,
  "logo_url": null
},{
  "_id": {
    "$oid": "62ac9cdbb1b111fc9ac0222b"
  },
  "ticker": "0071-HK",
  "name": "MIRAMAR HOTEL",
  "category": "Equity",
  "board_lot": 1000,
  "industry_x": "Hotels & Restaurants & Leisure",
  "nominal": "14.340",
  "turnover": "456,020",
  "mkt_cap": {
    "$numberLong": "9908000000"
  },
  "pct_yield": "3.208",
  "pe_ratio": "29.875",
  "sector": null,
  "country": null,
  "website": null,
  "industry_y": null,
  "current_price": null,
  "total_cash": null,
  "total_debt": null,
  "total_revenue": null,
  "total_cash_per_share": null,
  "financial_currency": null,
  "short_name": null,
  "long_name": null,
  "exchange_timezone_name": null,
  "quote_type": null,
  "logo_url": null
},{
  "_id": {
    "$oid": "62ac9cdbb1b111fc9ac0222c"
  },
  "ticker": "0072-HK",
  "name": "META MEDIA",
  "category": "Equity",
  "board_lot": 2000,
  "industry_x": "Media",
  "nominal": "0.305",
  "turnover": "77,610",
  "mkt_cap": 133698000,
  "pct_yield": "0.000",
  "pe_ratio": "N/A",
  "sector": null,
  "country": null,
  "website": null,
  "industry_y": null,
  "current_price": null,
  "total_cash": null,
  "total_debt": null,
  "total_revenue": null,
  "total_cash_per_share": null,
  "financial_currency": null,
  "short_name": null,
  "long_name": null,
  "exchange_timezone_name": null,
  "quote_type": null,
  "logo_url": null
},{
  "_id": {
    "$oid": "62ac9cdbb1b111fc9ac0222d"
  },
  "ticker": "0073-HK",
  "name": "ASIAN CITRUS",
  "category": "Equity",
  "board_lot": 1000,
  "industry_x": "Agricultural Products",
  "nominal": "0.097",
  "turnover": "4,977",
  "mkt_cap": 242465000,
  "pct_yield": "0.000",
  "pe_ratio": "27.640",
  "sector": null,
  "country": null,
  "website": null,
  "industry_y": null,
  "current_price": null,
  "total_cash": null,
  "total_debt": null,
  "total_revenue": null,
  "total_cash_per_share": null,
  "financial_currency": null,
  "short_name": null,
  "long_name": null,
  "exchange_timezone_name": null,
  "quote_type": null,
  "logo_url": null
},{
  "_id": {
    "$oid": "62ac9cdbb1b111fc9ac0222e"
  },
  "ticker": "0075-HK",
  "name": "Y.T. REALTY",
  "category": "Equity",
  "board_lot": 2000,
  "industry_x": "Properties",
  "nominal": "1.300",
  "turnover": "0.000",
  "mkt_cap": 1038999999,
  "pct_yield": "0.000",
  "pe_ratio": "N/A",
  "sector": null,
  "country": null,
  "website": null,
  "industry_y": null,
  "current_price": null,
  "total_cash": null,
  "total_debt": null,
  "total_revenue": null,
  "total_cash_per_share": null,
  "financial_currency": null,
  "short_name": null,
  "long_name": null,
  "exchange_timezone_name": null,
  "quote_type": null,
  "logo_url": null
},{
  "_id": {
    "$oid": "62ac9cdbb1b111fc9ac0222f"
  },
  "ticker": "0076-HK",
  "name": "ELATE HOLDINGS",
  "category": "Equity",
  "board_lot": 4000,
  "industry_x": "Industrials",
  "nominal": "0.034",
  "turnover": "557,378",
  "mkt_cap": 238225000,
  "pct_yield": "0.000",
  "pe_ratio": "6.188",
  "sector": null,
  "country": null,
  "website": null,
  "industry_y": null,
  "current_price": null,
  "total_cash": null,
  "total_debt": null,
  "total_revenue": null,
  "total_cash_per_share": null,
  "financial_currency": null,
  "short_name": null,
  "long_name": null,
  "exchange_timezone_name": null,
  "quote_type": null,
  "logo_url": null
},{
  "_id": {
    "$oid": "62ac9cdbb1b111fc9ac02230"
  },
  "ticker": "0077-HK",
  "name": "AMS TRANSPORT",
  "category": "Equity",
  "board_lot": 2000,
  "industry_x": "Transportation",
  "nominal": "0.740",
  "turnover": "7,400",
  "mkt_cap": 201216000,
  "pct_yield": "9.460",
  "pe_ratio": "9.215",
  "sector": null,
  "country": null,
  "website": null,
  "industry_y": null,
  "current_price": null,
  "total_cash": null,
  "total_debt": null,
  "total_revenue": null,
  "total_cash_per_share": null,
  "financial_currency": null,
  "short_name": null,
  "long_name": null,
  "exchange_timezone_name": null,
  "quote_type": null,
  "logo_url": null
},{
  "_id": {
    "$oid": "62ac9cdbb1b111fc9ac02231"
  },
  "ticker": "0078-HK",
  "name": "REGAL INT'L",
  "category": "Equity",
  "board_lot": 2000,
  "industry_x": "Hotels & Restaurants & Leisure",
  "nominal": "3.150",
  "turnover": "31,480",
  "mkt_cap": {
    "$numberLong": "2831000000"
  },
  "pct_yield": "0.000",
  "pe_ratio": "N/A",
  "sector": null,
  "country": null,
  "website": null,
  "industry_y": null,
  "current_price": null,
  "total_cash": null,
  "total_debt": null,
  "total_revenue": null,
  "total_cash_per_share": null,
  "financial_currency": null,
  "short_name": null,
  "long_name": null,
  "exchange_timezone_name": null,
  "quote_type": null,
  "logo_url": null
},{
  "_id": {
    "$oid": "62ac9cdbb1b111fc9ac02232"
  },
  "ticker": "0079-HK",
  "name": "CENTURY LEGEND",
  "category": "Equity",
  "board_lot": 4000,
  "industry_x": "Commercial & Professional Services",
  "nominal": "0.117",
  "turnover": "8,440",
  "mkt_cap": 38151000,
  "pct_yield": "0.000",
  "pe_ratio": "N/A",
  "sector": null,
  "country": null,
  "website": null,
  "industry_y": null,
  "current_price": null,
  "total_cash": null,
  "total_debt": null,
  "total_revenue": null,
  "total_cash_per_share": null,
  "financial_currency": null,
  "short_name": null,
  "long_name": null,
  "exchange_timezone_name": null,
  "quote_type": null,
  "logo_url": null
},{
  "_id": {
    "$oid": "62ac9cdbb1b111fc9ac02233"
  },
  "ticker": "0080-HK",
  "name": "CNEWECON FUND",
  "category": "Equity",
  "board_lot": 10000,
  "industry_x": "Other Financials",
  "nominal": "0.180",
  "turnover": "49,628",
  "mkt_cap": 233338000,
  "pct_yield": "0.000",
  "pe_ratio": "N/A",
  "sector": null,
  "country": null,
  "website": null,
  "industry_y": null,
  "current_price": null,
  "total_cash": null,
  "total_debt": null,
  "total_revenue": null,
  "total_cash_per_share": null,
  "financial_currency": null,
  "short_name": null,
  "long_name": null,
  "exchange_timezone_name": null,
  "quote_type": null,
  "logo_url": null
},{
  "_id": {
    "$oid": "62ac9cdbb1b111fc9ac02234"
  },
  "ticker": "0081-HK",
  "name": "CH OVS G OCEANS",
  "category": "Equity",
  "board_lot": 1000,
  "industry_x": "Properties",
  "nominal": "3.960",
  "turnover": "8.781M",
  "mkt_cap": {
    "$numberLong": "13557000000"
  },
  "pct_yield": "9.596",
  "pe_ratio": "2.295",
  "sector": null,
  "country": null,
  "website": null,
  "industry_y": null,
  "current_price": null,
  "total_cash": null,
  "total_debt": null,
  "total_revenue": null,
  "total_cash_per_share": null,
  "financial_currency": null,
  "short_name": null,
  "long_name": null,
  "exchange_timezone_name": null,
  "quote_type": null,
  "logo_url": null
},{
  "_id": {
    "$oid": "62ac9cdbb1b111fc9ac02235"
  },
  "ticker": "0082-HK",
  "name": "CRAZY SPORTS",
  "category": "Equity",
  "board_lot": 2000,
  "industry_x": "Software & Services",
  "nominal": "0.300",
  "turnover": "1.385M",
  "mkt_cap": 1358000000,
  "pct_yield": "0.000",
  "pe_ratio": "8.646",
  "sector": null,
  "country": null,
  "website": null,
  "industry_y": null,
  "current_price": null,
  "total_cash": null,
  "total_debt": null,
  "total_revenue": null,
  "total_cash_per_share": null,
  "financial_currency": null,
  "short_name": null,
  "long_name": null,
  "exchange_timezone_name": null,
  "quote_type": null,
  "logo_url": null
},{
  "_id": {
    "$oid": "62ac9cdbb1b111fc9ac02236"
  },
  "ticker": "0083-HK",
  "name": "SINO LAND",
  "category": "Equity",
  "board_lot": 2000,
  "industry_x": "Properties",
  "nominal": "11.000",
  "turnover": "144.569M",
  "mkt_cap": {
    "$numberLong": "84900000000"
  },
  "pct_yield": "7.636",
  "pe_ratio": "8.271",
  "sector": null,
  "country": null,
  "website": null,
  "industry_y": null,
  "current_price": null,
  "total_cash": null,
  "total_debt": null,
  "total_revenue": null,
  "total_cash_per_share": null,
  "financial_currency": null,
  "short_name": null,
  "long_name": null,
  "exchange_timezone_name": null,
  "quote_type": null,
  "logo_url": null
},{
  "_id": {
    "$oid": "62ac9cdbb1b111fc9ac02237"
  },
  "ticker": "0084-HK",
  "name": "STELUX HOLDINGS",
  "category": "Equity",
  "board_lot": 1000,
  "industry_x": "Jewellery & Watches",
  "nominal": "0.059",
  "turnover": "9,049",
  "mkt_cap": 61742000,
  "pct_yield": "0.000",
  "pe_ratio": "N/A",
  "sector": null,
  "country": null,
  "website": null,
  "industry_y": null,
  "current_price": null,
  "total_cash": null,
  "total_debt": null,
  "total_revenue": null,
  "total_cash_per_share": null,
  "financial_currency": null,
  "short_name": null,
  "long_name": null,
  "exchange_timezone_name": null,
  "quote_type": null,
  "logo_url": null
},{
  "_id": {
    "$oid": "62ac9cdbb1b111fc9ac02238"
  },
  "ticker": "0085-HK",
  "name": "CE HUADA TECH",
  "category": "Equity",
  "board_lot": 2000,
  "industry_x": "Semiconductors",
  "nominal": "0.750",
  "turnover": "781,832",
  "mkt_cap": 1522000000,
  "pct_yield": "2.533",
  "pe_ratio": "12.136",
  "sector": null,
  "country": null,
  "website": null,
  "industry_y": null,
  "current_price": null,
  "total_cash": null,
  "total_debt": null,
  "total_revenue": null,
  "total_cash_per_share": null,
  "financial_currency": null,
  "short_name": null,
  "long_name": null,
  "exchange_timezone_name": null,
  "quote_type": null,
  "logo_url": null
},{
  "_id": {
    "$oid": "62ac9cdbb1b111fc9ac02239"
  },
  "ticker": "0086-HK",
  "name": "SUN HUNG KAI CO",
  "category": "Equity",
  "board_lot": 1000,
  "industry_x": "Other Financials",
  "nominal": "3.580",
  "turnover": "1.264M",
  "mkt_cap": {
    "$numberLong": "7062000000"
  },
  "pct_yield": "8.380",
  "pe_ratio": "2.509",
  "sector": null,
  "country": null,
  "website": null,
  "industry_y": null,
  "current_price": null,
  "total_cash": null,
  "total_debt": null,
  "total_revenue": null,
  "total_cash_per_share": null,
  "financial_currency": null,
  "short_name": null,
  "long_name": null,
  "exchange_timezone_name": null,
  "quote_type": null,
  "logo_url": null
},{
  "_id": {
    "$oid": "62ac9cdbb1b111fc9ac0223a"
  },
  "ticker": "0087-HK",
  "name": "SWIRE PACIFIC B",
  "category": "Equity",
  "board_lot": 2500,
  "industry_x": "Conglomerates",
  "nominal": "7.600",
  "turnover": "8.235M",
  "mkt_cap": {
    "$numberLong": "22662000000"
  },
  "pct_yield": "6.842",
  "pe_ratio": "16.889",
  "sector": null,
  "country": null,
  "website": null,
  "industry_y": null,
  "current_price": null,
  "total_cash": null,
  "total_debt": null,
  "total_revenue": null,
  "total_cash_per_share": null,
  "financial_currency": null,
  "short_name": null,
  "long_name": null,
  "exchange_timezone_name": null,
  "quote_type": null,
  "logo_url": null
},{
  "_id": {
    "$oid": "62ac9cdbb1b111fc9ac0223b"
  },
  "ticker": "0088-HK",
  "name": "TAI CHEUNG HOLD",
  "category": "Equity",
  "board_lot": 1000,
  "industry_x": "Properties",
  "nominal": "4.510",
  "turnover": "27,020",
  "mkt_cap": {
    "$numberLong": "2785000000"
  },
  "pct_yield": "5.322",
  "pe_ratio": "N/A",
  "sector": null,
  "country": null,
  "website": null,
  "industry_y": null,
  "current_price": null,
  "total_cash": null,
  "total_debt": null,
  "total_revenue": null,
  "total_cash_per_share": null,
  "financial_currency": null,
  "short_name": null,
  "long_name": null,
  "exchange_timezone_name": null,
  "quote_type": null,
  "logo_url": null
},{
  "_id": {
    "$oid": "62ac9cdbb1b111fc9ac0223c"
  },
  "ticker": "0089-HK",
  "name": "TAI SANG LAND",
  "category": "Equity",
  "board_lot": 1000,
  "industry_x": "Properties",
  "nominal": "4.050",
  "turnover": "98,117",
  "mkt_cap": 1165000000,
  "pct_yield": "5.432",
  "pe_ratio": "1.841",
  "sector": null,
  "country": null,
  "website": null,
  "industry_y": null,
  "current_price": null,
  "total_cash": null,
  "total_debt": null,
  "total_revenue": null,
  "total_cash_per_share": null,
  "financial_currency": null,
  "short_name": null,
  "long_name": null,
  "exchange_timezone_name": null,
  "quote_type": null,
  "logo_url": null
},{
  "_id": {
    "$oid": "62ac9cdbb1b111fc9ac0223d"
  },
  "ticker": "0090-HK",
  "name": "PUXING ENERGY",
  "category": "Equity",
  "board_lot": 2000,
  "industry_x": "Utilities",
  "nominal": "0.610",
  "turnover": "12,240",
  "mkt_cap": 279746000,
  "pct_yield": "9.180",
  "pe_ratio": "2.307",
  "sector": null,
  "country": null,
  "website": null,
  "industry_y": null,
  "current_price": null,
  "total_cash": null,
  "total_debt": null,
  "total_revenue": null,
  "total_cash_per_share": null,
  "financial_currency": null,
  "short_name": null,
  "long_name": null,
  "exchange_timezone_name": null,
  "quote_type": null,
  "logo_url": null
},{
  "_id": {
    "$oid": "62ac9cdbb1b111fc9ac0223e"
  },
  "ticker": "0091-HK",
  "name": "GOLDEN CEN INTL",
  "category": "Equity",
  "board_lot": 10000,
  "industry_x": "Oil & Gas",
  "nominal": "0.189",
  "turnover": "679,610",
  "mkt_cap": 841843000,
  "pct_yield": "0.000",
  "pe_ratio": "N/A",
  "sector": null,
  "country": null,
  "website": null,
  "industry_y": null,
  "current_price": null,
  "total_cash": null,
  "total_debt": null,
  "total_revenue": null,
  "total_cash_per_share": null,
  "financial_currency": null,
  "short_name": null,
  "long_name": null,
  "exchange_timezone_name": null,
  "quote_type": null,
  "logo_url": null
},{
  "_id": {
    "$oid": "62ac9cdbb1b111fc9ac0223f"
  },
  "ticker": "0092-HK",
  "name": "CHAMPION TECH",
  "category": "Equity",
  "board_lot": 24000,
  "industry_x": "Oil & Gas",
  "nominal": "0.076",
  "turnover": "27.417",
  "mkt_cap": 207885000,
  "pct_yield": "0.000",
  "pe_ratio": "N/A",
  "sector": null,
  "country": null,
  "website": null,
  "industry_y": null,
  "current_price": null,
  "total_cash": null,
  "total_debt": null,
  "total_revenue": null,
  "total_cash_per_share": null,
  "financial_currency": null,
  "short_name": null,
  "long_name": null,
  "exchange_timezone_name": null,
  "quote_type": null,
  "logo_url": null
},{
  "_id": {
    "$oid": "62ac9cdbb1b111fc9ac02240"
  },
  "ticker": "0093-HK",
  "name": "TERMBRAY IND",
  "category": "Equity",
  "board_lot": 2000,
  "industry_x": "Properties",
  "nominal": "0.206",
  "turnover": "0.000",
  "mkt_cap": 549534000,
  "pct_yield": "0.000",
  "pe_ratio": "25.750",
  "sector": null,
  "country": null,
  "website": null,
  "industry_y": null,
  "current_price": null,
  "total_cash": null,
  "total_debt": null,
  "total_revenue": null,
  "total_cash_per_share": null,
  "financial_currency": null,
  "short_name": null,
  "long_name": null,
  "exchange_timezone_name": null,
  "quote_type": null,
  "logo_url": null
},{
  "_id": {
    "$oid": "62ac9cdbb1b111fc9ac02241"
  },
  "ticker": "0094-HK",
  "name": "GREENHEART GP",
  "category": "Equity",
  "board_lot": 2000,
  "industry_x": "Paper & Forest Products",
  "nominal": "0.098",
  "turnover": "0.000",
  "mkt_cap": 181789000,
  "pct_yield": "0.000",
  "pe_ratio": "N/A",
  "sector": null,
  "country": null,
  "website": null,
  "industry_y": null,
  "current_price": null,
  "total_cash": null,
  "total_debt": null,
  "total_revenue": null,
  "total_cash_per_share": null,
  "financial_currency": null,
  "short_name": null,
  "long_name": null,
  "exchange_timezone_name": null,
  "quote_type": null,
  "logo_url": null
},{
  "_id": {
    "$oid": "62ac9cdbb1b111fc9ac02242"
  },
  "ticker": "0095-HK",
  "name": "LVGEM CHINA",
  "category": "Equity",
  "board_lot": 2000,
  "industry_x": "Properties",
  "nominal": "1.010",
  "turnover": "14.998M",
  "mkt_cap": {
    "$numberLong": "5149000000"
  },
  "pct_yield": "0.000",
  "pe_ratio": "3.819",
  "sector": null,
  "country": null,
  "website": null,
  "industry_y": null,
  "current_price": null,
  "total_cash": null,
  "total_debt": null,
  "total_revenue": null,
  "total_cash_per_share": null,
  "financial_currency": null,
  "short_name": null,
  "long_name": null,
  "exchange_timezone_name": null,
  "quote_type": null,
  "logo_url": null
},{
  "_id": {
    "$oid": "62ac9cdbb1b111fc9ac02243"
  },
  "ticker": "0096-HK",
  "name": "YUSEI",
  "category": "Equity",
  "board_lot": 2000,
  "industry_x": "Industrials",
  "nominal": "0.680",
  "turnover": "1,380",
  "mkt_cap": 432854000,
  "pct_yield": "2.235",
  "pe_ratio": "7.177",
  "sector": null,
  "country": null,
  "website": null,
  "industry_y": null,
  "current_price": null,
  "total_cash": null,
  "total_debt": null,
  "total_revenue": null,
  "total_cash_per_share": null,
  "financial_currency": null,
  "short_name": null,
  "long_name": null,
  "exchange_timezone_name": null,
  "quote_type": null,
  "logo_url": null
},{
  "_id": {
    "$oid": "62ac9cdbb1b111fc9ac02244"
  },
  "ticker": "0097-HK",
  "name": "HENDERSON INV",
  "category": "Equity",
  "board_lot": 1000,
  "industry_x": "Retailers",
  "nominal": "0.350",
  "turnover": "80,160",
  "mkt_cap": 1067000000,
  "pct_yield": "5.714",
  "pe_ratio": "31.818",
  "sector": null,
  "country": null,
  "website": null,
  "industry_y": null,
  "current_price": null,
  "total_cash": null,
  "total_debt": null,
  "total_revenue": null,
  "total_cash_per_share": null,
  "financial_currency": null,
  "short_name": null,
  "long_name": null,
  "exchange_timezone_name": null,
  "quote_type": null,
  "logo_url": null
},{
  "_id": {
    "$oid": "62ac9cdbb1b111fc9ac02245"
  },
  "ticker": "0098-HK",
  "name": "XINGFA ALUM",
  "category": "Equity",
  "board_lot": 1000,
  "industry_x": "Diversified Metals & Minerals",
  "nominal": "9.110",
  "turnover": "0.000",
  "mkt_cap": {
    "$numberLong": "3826000000"
  },
  "pct_yield": "8.782",
  "pe_ratio": "3.673",
  "sector": null,
  "country": null,
  "website": null,
  "industry_y": null,
  "current_price": null,
  "total_cash": null,
  "total_debt": null,
  "total_revenue": null,
  "total_cash_per_share": null,
  "financial_currency": null,
  "short_name": null,
  "long_name": null,
  "exchange_timezone_name": null,
  "quote_type": null,
  "logo_url": null
},{
  "_id": {
    "$oid": "62ac9cdbb1b111fc9ac02246"
  },
  "ticker": "0099-HK",
  "name": "WONG'S INT'L",
  "category": "Equity",
  "board_lot": 1000,
  "industry_x": "IT Hardware",
  "nominal": "2.015",
  "turnover": "0.000",
  "mkt_cap": 964145000,
  "pct_yield": "1.985",
  "pe_ratio": "10.605",
  "sector": null,
  "country": null,
  "website": null,
  "industry_y": null,
  "current_price": null,
  "total_cash": null,
  "total_debt": null,
  "total_revenue": null,
  "total_cash_per_share": null,
  "financial_currency": null,
  "short_name": null,
  "long_name": null,
  "exchange_timezone_name": null,
  "quote_type": null,
  "logo_url": null
}]